tap_qualified/__init__.py
tap_qualified/client.py
tap_qualified/schemas/bot_conversations.json
tap_qualified/schemas/rep_conversations.json
tap_qualified/streams.py
tap_qualified/tap.py
tap_qualified/tests/__init__.py
tap_qualified/tests/conftest.py
tap_qualified/tests/test_core.py
tap_qualified-1.0.1.dist-info/entry_points.txt
tap_qualified-1.0.1.dist-info/LICENSE
tap_qualified-1.0.1.dist-info/WHEEL
tap_qualified-1.0.1.dist-info/METADATA
tap_qualified-1.0.1.dist-info/RECORD
