Metadata-Version: 2.1
Name: tap-qualified
Version: 1.0.1
Summary: `tap-qualified` is a Singer tap for Qualified, built with the Meltano Singer SDK.
Home-page: https://github.com/z3z1ma/tap-qualified
License: Apache 2.0
Keywords: ELT,Qualified
Author: Alex Butler
Requires-Python: >=3.8,<3.12
Classifier: Development Status :: 5 - Production/Stable
Classifier: Environment :: Console
Classifier: Intended Audience :: Developers
Classifier: License :: OSI Approved :: MIT License
Classifier: License :: Other/Proprietary License
Classifier: Natural Language :: English
Classifier: Operating System :: OS Independent
Classifier: Programming Language :: Python :: 3
Classifier: Programming Language :: Python :: 3.8
Classifier: Programming Language :: Python :: 3.9
Classifier: Programming Language :: Python :: 3.10
Classifier: Programming Language :: Python :: 3.11
Classifier: Programming Language :: Python :: 3.10
Classifier: Programming Language :: Python :: 3.8
Classifier: Programming Language :: Python :: 3.9
Classifier: Topic :: Software Development :: Libraries :: Python Modules
Provides-Extra: s3
Requires-Dist: fs-s3fs (>=1.1.1); extra == "s3"
Requires-Dist: requests (>=2.28.1)
Requires-Dist: singer-sdk (>=0.19.0,<1)
Project-URL: Repository, https://github.com/z3z1ma/tap-qualified
